[{"code": "ST08-001", "rarity": "L", "card_type": "LEADER", "card_name": "Monkey.D.Luffy", "cost": null, "life": 5, "power": 5000, "counter": null, "color": ["Black"], "attribute": "Strike", "feature": ["Straw Hat Crew"], "card_image_link": ["images/cardlist/card/ST08-001.png?250701"], "text": "[Your Turn] When a Character is K.O.'d, give up to 1 rested DON!! card to this Leader.", "trigger": null, "card_sets": "Card Set(s)-Monkey D. Luffy-[ST-08]"}, {"code": "ST08-002", "rarity": "SR", "card_type": "CHARACTER", "card_name": "Uta", "cost": 2, "life": null, "power": 3000, "counter": null, "color": ["Black"], "attribute": "Special", "feature": ["FILM"], "card_image_link": ["images/cardlist/card/ST08-002.png?250701"], "text": "This Character cannot be K.O.'d in battle by Leaders.[Activate: Main] You may rest this Character: Give up to 1 of your opponent's Characters \u22122 cost during this turn.", "trigger": null, "card_sets": "Card Set(s)-Monkey D. Luffy-[ST-08]"}, {"code": "ST08-003", "rarity": "C", "card_type": "CHARACTER", "card_name": "Gaimon", "cost": 2, "life": null, "power": 4000, "counter": 1000, "color": ["Black"], "attribute": "Wisdom", "feature": ["East Blue"], "card_image_link": ["images/cardlist/card/ST08-003.png?250701"], "text": null, "trigger": null, "card_sets": "Card Set(s)-Monkey D. Luffy-[ST-08]"}, {"code": "ST08-004", "rarity": "C", "card_type": "CHARACTER", "card_name": "Koby", "cost": 4, "life": null, "power": 1000, "counter": 1000, "color": ["Black"], "attribute": "Strike", "feature": ["Navy"], "card_image_link": ["images/cardlist/card/ST08-004.png?250701"], "text": "[Activate: Main] You may rest this Character: K.O. up to 1 of your opponent's Characters with a cost of 2 or less.", "trigger": null, "card_sets": "Card Set(s)-Monkey D. Luffy-[ST-08]"}, {"code": "ST08-005", "rarity": "SR", "card_type": "CHARACTER", "card_name": "Shanks", "cost": 9, "life": null, "power": 10000, "counter": null, "color": ["Black"], "attribute": "Slash", "feature": ["Red-Haired Pirates"], "card_image_link": ["images/cardlist/card/ST08-005.png?250701"], "text": "[On Play] You may trash 1 card from your hand: K.O. all Characters with a cost of 1 or less.", "trigger": null, "card_sets": "Card Set(s)-Monkey D. Luffy-[ST-08]"}, {"code": "ST08-006", "rarity": "C", "card_type": "CHARACTER", "card_name": "Shirahoshi", "cost": 4, "life": null, "power": null, "counter": 1000, "color": ["Black"], "attribute": "Wisdom", "feature": ["Merfolk"], "card_image_link": ["images/cardlist/card/ST08-006.png?250701"], "text": "[Blocker] (After your opponent declares an attack, you may rest this card to make it the new target of the attack.)[On Play] Give up to 1 of your opponent's Characters \u22124 cost during this turn.", "trigger": null, "card_sets": "Card Set(s)-Monkey D. Luffy-[ST-08]"}, {"code": "ST08-007", "rarity": "C", "card_type": "CHARACTER", "card_name": "Nefeltari Vivi", "cost": 3, "life": null, "power": 1000, "counter": 1000, "color": ["Black"], "attribute": "Slash", "feature": ["Alabasta"], "card_image_link": ["images/cardlist/card/ST08-007.png?250701"], "text": "[Blocker] (After your opponent declares an attack, you may rest this card to make it the new target of the attack.)", "trigger": "[Trigger] Play this card.", "card_sets": "Card Set(s)-Monkey D. Luffy-[ST-08]"}, {"code": "ST08-008", "rarity": "C", "card_type": "CHARACTER", "card_name": "Higuma", "cost": 1, "life": null, "power": 2000, "counter": 1000, "color": ["Black"], "attribute": "Slash", "feature": ["Mountain Bandits"], "card_image_link": ["images/cardlist/card/ST08-008.png?250701"], "text": "[On Play] Give up to 1 of your opponent's Characters \u22122 cost during this turn.", "trigger": null, "card_sets": "Card Set(s)-Monkey D. Luffy-[ST-08]"}, {"code": "ST08-009", "rarity": "C", "card_type": "CHARACTER", "card_name": "Makino", "cost": 2, "life": null, "power": null, "counter": 2000, "color": ["Black"], "attribute": "Wisdom", "feature": ["Windmill Village"], "card_image_link": ["images/cardlist/card/ST08-009.png?250701"], "text": "[On Play] If there is a Character with a cost of 0, draw 1 card.", "trigger": null, "card_sets": "Card Set(s)-Monkey D. Luffy-[ST-08]"}, {"code": "ST08-010", "rarity": "C", "card_type": "CHARACTER", "card_name": "Monkey.D.Garp", "cost": 5, "life": null, "power": 7000, "counter": 1000, "color": ["Black"], "attribute": "Strike", "feature": ["Navy"], "card_image_link": ["images/cardlist/card/ST08-010.png?250701"], "text": null, "trigger": null, "card_sets": "Card Set(s)-Monkey D. Luffy-[ST-08]"}, {"code": "ST08-011", "rarity": "C", "card_type": "CHARACTER", "card_name": "Monkey.D.Luffy", "cost": 3, "life": null, "power": 5000, "counter": 1000, "color": ["Black"], "attribute": "Strike", "feature": ["Straw Hat Crew"], "card_image_link": ["images/cardlist/card/ST08-011.png?250701"], "text": null, "trigger": null, "card_sets": "Card Set(s)-Monkey D. Luffy-[ST-08]"}, {"code": "ST08-012", "rarity": "C", "card_type": "CHARACTER", "card_name": "Laboon", "cost": 4, "life": null, "power": 6000, "counter": 1000, "color": ["Black"], "attribute": "Strike", "feature": ["Animal"], "card_image_link": ["images/cardlist/card/ST08-012.png?250701"], "text": null, "trigger": null, "card_sets": "Card Set(s)-Monkey D. Luffy-[ST-08]"}, {"code": "ST08-013", "rarity": "C", "card_type": "CHARACTER", "card_name": "Mr.2.Bon.Kurei(Bentham)", "cost": 5, "life": null, "power": 6000, "counter": null, "color": ["Black"], "attribute": "Strike", "feature": ["Former Baroque Works"], "card_image_link": ["images/cardlist/card/ST08-013.png?250701"], "text": "[DON!! x1] At the end of a battle in which this Character battles your opponent's Character, you may K.O. the opponent\u2019s Character you battled with. If you do, K.O. this Character.", "trigger": null, "card_sets": "Card Set(s)-Monkey D. Luffy-[ST-08]"}, {"code": "ST08-014", "rarity": "C", "card_type": "EVENT", "card_name": "Gum-Gum Bell", "cost": 2, "life": null, "power": null, "counter": null, "color": ["Black"], "attribute": null, "feature": ["Straw Hat Crew"], "card_image_link": ["images/cardlist/card/ST08-014.png?250701"], "text": "[Main] You may add 1 card from the top of your Life cards to your hand: Give up to 1 of your opponent's Characters \u22127 cost during this turn.", "trigger": "[Trigger] Add up to 1 black Character card with a cost of 2 or less from your trash to your hand.", "card_sets": "Card Set(s)-Monkey D. Luffy-[ST-08]"}, {"code": "ST08-015", "rarity": "C", "card_type": "EVENT", "card_name": "Gum-Gum Pistol", "cost": 3, "life": null, "power": null, "counter": null, "color": ["Black"], "attribute": null, "feature": ["Straw Hat Crew"], "card_image_link": ["images/cardlist/card/ST08-015.png?250701"], "text": "[Main] K.O. up to 1 of your opponent's Characters with a cost of 2 or less.", "trigger": "[Trigger] Draw 1 card.", "card_sets": "Card Set(s)-Monkey D. Luffy-[ST-08]"}]